LICENSE
MANIFEST.in
README.rst
example.py
setup.cfg
setup.py
tox.ini
Kudzu.egg-info/PKG-INFO
Kudzu.egg-info/SOURCES.txt
Kudzu.egg-info/dependency_links.txt
Kudzu.egg-info/not-zip-safe
Kudzu.egg-info/top_level.txt
kudzu/__init__.py
kudzu/context.py
kudzu/logging.py
kudzu/middleware.py
tests/test_context.py
tests/test_logging.py
tests/test_middleware.py